DataHandler/__init__.py
DataHandler/data_handler.py
data_handler_csv-0.0.6.dist-info/LICENSE
data_handler_csv-0.0.6.dist-info/METADATA
data_handler_csv-0.0.6.dist-info/WHEEL
data_handler_csv-0.0.6.dist-info/top_level.txt
data_handler_csv-0.0.6.dist-info/RECORD
