Metadata-Version: 2.1
Name: data-handler-csv
Version: 0.0.6
Summary: useful function for my work
Author: LALAPOPA
Author-email: la_la_popa@vk.com
Project-URL: Source Code, https://github.com/lalapopa/data_handler_csv
Keywords: csv,column,interpolation,data taker
Classifier: Development Status :: 1 - Planning
Classifier: Programming Language :: Python :: 3.9
Classifier: License :: OSI Approved :: MIT License
License-File: LICENSE
Requires-Dist: numpy
Requires-Dist: pandas
Requires-Dist: scipy
